datatrans/__init__.py
datatrans/admin.py
datatrans/apps.py
datatrans/config.py
datatrans/models.py
datatrans/signals.py
datatrans/urls.py
datatrans/gateway/__init__.py
datatrans/gateway/money_xml_converters.py
datatrans/gateway/notification.py
datatrans/gateway/payment_parameters.py
datatrans/gateway/payment_with_alias.py
datatrans/gateway/refunding.py
datatrans/gateway/utils.py
datatrans/migrations/0001_initial.py
datatrans/migrations/0002_stricter_expiry_validation.py
datatrans/migrations/0003_add_modified_field.py
datatrans/migrations/0004_alias_registration_fields_optional.py
datatrans/migrations/0005_optional_aliasregistration_transaction_id.py
datatrans/migrations/0006_no_more_default_value_for_amounts.py
datatrans/migrations/__init__.py
datatrans/templates/admin/datatrans/form.html
datatrans/templates/datatrans/example/datatrans_form.html
datatrans/templates/datatrans/example/form.html
datatrans/views/__init__.py
datatrans/views/example.py
datatrans/views/webhook.py
django_datatrans_gateway-1.0.15.dist-info/LICENSE
django_datatrans_gateway-1.0.15.dist-info/METADATA
django_datatrans_gateway-1.0.15.dist-info/WHEEL
django_datatrans_gateway-1.0.15.dist-info/top_level.txt
django_datatrans_gateway-1.0.15.dist-info/RECORD
