Metadata-Version: 2.1
Name: django-datatrans-gateway
Version: 1.0.15
Summary: Integrate django with the datatrans payment service provider
Home-page: https://github.com/skioo/django-datatrans-gateway
Author: Nicholas Wolff
Author-email: nwolff@gmail.com
License: MIT
Download-URL: https://pypi.python.org/pypi/django-datatrans-gateway
Platform: UNKNOWN
Classifier: Development Status :: 5 - Production/Stable
Classifier: Environment :: Web Environment
Classifier: Framework :: Django :: 2.0
Classifier: Framework :: Django :: 2.1
Classifier: Framework :: Django :: 2.2
Classifier: Framework :: Django :: 3.2
Classifier: Intended Audience :: Developers
Classifier: License :: OSI Approved :: MIT License
Classifier: Operating System :: OS Independent
Classifier: Programming Language :: Python
Classifier: Programming Language :: Python :: 3.6
Classifier: Programming Language :: Python :: 3.7
Classifier: Programming Language :: Python :: 3.8
Requires-Dist: Django (>=2.0)
Requires-Dist: django-money
Requires-Dist: requests
Requires-Dist: defusedxml
Requires-Dist: structlog
